Workbook

Sheet Instrucciones
A1: 🗂️ PLANTILLA DE PLANIFICACIÓN DE RECURSOS — Taimbox
A3: Esta plantilla tiene 4 hojas de trabajo + esta página de instrucciones.
A4: Todas las fórmulas están conectadas: edita los datos base y el resto se actualiza solo.
A5: Las celdas con fórmula están protegidas (fondo gris claro); solo puedes editar las celdas de entrada.
A7: ── HOJA "Equipo" ──
A8: • Rellena una fila por persona del equipo (nombre, rol, jornada, coste hora).
A9: • Ajusta las horas de reuniones, admin/formación y ausencias cada semana.
A10: • La columna "Capacidad neta" se calcula automáticamente: Jornada − Reuniones − Admin − Ausencias.
A11: • "Coste hora" es el coste interno (no precio de venta); se usa para calcular márgenes en "Proyectos" e "Insights".
A13: ── HOJA "Proyectos" ──
A14: • Un proyecto (o cliente-servicio) por fila. Fee y horas presupuestadas son mensuales.
A15: • Las columnas "Horas asignadas semana", "Pacing", "Coste semana" y "Margen" se calculan desde "Asignación".
... A43: • taimbox.com/planificador-recursos

Sheet Equipo
A1: Persona | B1: Rol / Departamento | C1: Jornada (h/sem) | D1: Reuniones (h) | E1: Admin / formación (h) | F1: Ausencias semana (h) | G1: Capacidad neta (h) | H1: Coste hora (€)
A2: Ana López | B2: Paid Media | C2: 40 | D2: 6 | E2: 2 | F2: 0 | G2: =C2-D2-E2-F2 | H2: 35
A3: Luis García | B3: Diseño | C3: 40 | D3: 4 | E3: 2 | F3: 0 | G3: =C3-D3-E3-F3 | H3: 30
A4: María Pérez | B4: Cuentas / Traffic | C4: 40 | D4: 8 | E4: 3 | F4: 0 | G4: =C4-D4-E4-F4 | H4: 40
A5: Carlos Ruiz | B5: SEO / Contenidos | C5: 40 | D5: 5 | E5: 2 | F5: 0 | G5: =C5-D5-E5-F5 | H5: 32
A6: Elena Martín | B6: Social Media | C6: 40 | D6: 4 | E6: 2 | F6: 0 | G6: =C6-D6-E6-F6 | H6: 28
A7: Jorge Navarro | B7: Desarrollo Web | C7: 40 | D7: 3 | E7: 1 | F7: 0 | G7: =C7-D7-E7-F7 | H7: 45
A8: Sara Díaz | B8: Estrategia / Dirección | C8: 40 | D8: 10 | E8: 4 | F8: 0 | G8: =C8-D8-E8-F8 | H8: 55
A9: Pablo Torres | B9: Diseño Junior | C9: 32 | D9: 3 | E9: 2 | F9: 0 | G9: =C9-D9-E9-F9 | H9: 22
A10: (Tu nombre) | B10: (Departamento) | C10: 40 | D10: 0 | E10: 0 | F10: 0 | G10: =C10-D10-E10-F10 | H10: 0
A11: (Tu nombre) | B11: (Departamento) | C11: 40 | D11: 0 | E11: 0 | F11: 0 | G11: =C11-D11-E11-F11 | H11: 0
A12: TOTALES | C12: =SUM(C2:C11) | D12: =SUM(D2:D11) | E12: =SUM(E2:E11) | F12: =SUM(F2:F11) | G12: =SUM(G2:G11)
A14: 📋 Rellena una fila por persona. "Capacidad neta" se calcula sola (Jornada − Reuniones − Admin − Ausencias). Actualiza "Ausencias semana" cada lunes.

Sheet Proyectos
A1: Proyecto / Cliente | B1: Tipo | C1: Fee mensual (€) | D1: Horas presup. / mes | E1: Horas asignadas semana | F1: Pacing horas (%) | G1: Coste semana est. (€) | H1: Margen mensual est. (€)
A2: Marca Alpha — Paid | B2: Retainer | C2: 4500 | D2: 60 | E2: =SUMIF(Asignacion!B:B,A2,Asignacion!D:D) | F2: =IFERROR(E2/(D2/4),0) | G2: =IFERROR(SUMPRODUCT((Asignacion!B$2:B$200=A2)*Asignacion!D$2:D$200*VLOOKUP(Asignacion!A$2:A$200,Equipo!A:H,8,FALSE)),0) | H2: =C2-(G2*4)
A3: Marca Alpha — Social | B3: Retainer | C3: 2000 | D3: 30 | E3: =SUMIF(Asignacion!B:B,A3,Asignacion!D:D) | F3: =IFERROR(E3/(D3/4),0) | G3: =IFERROR(SUMPRODUCT((Asignacion!B$2:B$200=A3)*Asignacion!D$2:D$200*VLOOKUP(Asignacion!A$2:A$200,Equipo!A:H,8,FALSE)),0) | H3: =C3-(G3*4)
A4: Marca Beta — Web | B4: Proyecto | C4: 8000 | D4: 100 | E4: =SUMIF(Asignacion!B:B,A4,Asignacion!D:D) | F4: =IFERROR(E4/(D4/4),0) | G4: =IFERROR(SUMPRODUCT((Asignacion!B$2:B$200=A4)*Asignacion!D$2:D$200*VLOOKUP(Asignacion!A$2:A$200,Equipo!A:H,8,FALSE)),0) | H4: =C4-(G4*4)
A5: Marca Gamma — SEO | B5: Retainer | C5: 3000 | D5: 45 | E5: =SUMIF(Asignacion!B:B,A5,Asignacion!D:D) | F5: =IFERROR(E5/(D5/4),0) | G5: =IFERROR(SUMPRODUCT((Asignacion!B$2:B$200=A5)*Asignacion!D$2:D$200*VLOOKUP(Asignacion!A$2:A$200,Equipo!A:H,8,FALSE)),0) | H5: =C5-(G5*4)
A6: Marca Delta — Branding | B6: Proyecto | C6: 6000 | D6: 80 | E6: =SUMIF(Asignacion!B:B,A6,Asignacion!D:D) | F6: =IFERROR(E6/(D6/4),0) | G6: =IFERROR(SUMPRODUCT((Asignacion!B$2:B$200=A6)*Asignacion!D$2:D$200*VLOOKUP(Asignacion!A$2:A$200,Equipo!A:H,8,FALSE)),0) | H6: =C6-(G6*4)
A7: Interno — Formación | B7: Interno | C7: 0 | D7: 20 | E7: =SUMIF(Asignacion!B:B,A7,Asignacion!D:D) | F7: =IFERROR(E7/(D7/4),0) | G7: =IFERROR(SUMPRODUCT((Asignacion!B$2:B$200=A7)*Asignacion!D$2:D$200*VLOOKUP(Asignacion!A$2:A$200,Equipo!A:H,8,FALSE)),0) | H7: =C7-(G7*4)
A8: (Proyecto) | B8: (Tipo) | C8: 0 | D8: 0 | E8: =SUMIF(Asignacion!B:B,A8,Asignacion!D:D) | F8: =IFERROR(E8/(D8/4),0) | G8: =IFERROR(SUMPRODUCT((Asignacion!B$2:B$200=A8)*Asignacion!D$2:D$200*VLOOKUP(Asignacion!A$2:A$200,Equipo!A:H,8,FALSE)),0) | H8: =C8-(G8*4)
A9: (Proyecto) | B9: (Tipo) | C9: 0 | D9: 0 | E9: =SUMIF(Asignacion!B:B,A9,Asignacion!D:D) | F9: =IFERROR(E9/(D9/4),0) | G9: =IFERROR(SUMPRODUCT((Asignacion!B$2:B$200=A9)*Asignacion!D$2:D$200*VLOOKUP(Asignacion!A$2:A$200,Equipo!A:H,8,FALSE)),0) | H9: =C9-(G9*4)
A10: TOTALES | C10: =SUM(C2:C9) | D10: =SUM(D2:D9) | E10: =SUM(E2:E9) | G10: =SUM(G2:G9) | H10: =SUM(H2:H9)
A12: 📋 Las horas y costes se calculan desde "Asignación". El pacing compara horas asignadas esta semana con la media semanal presupuestada (horas mes ÷ 4). Margen negativo aparece en rojo.

Sheet Asignacion
A1: Persona | B1: Proyecto / Cliente | C1: Semana | D1: Horas asignadas | E1: Notas
A2: Ana López | B2: Marca Alpha — Paid | C2: S12 (17-21 mar) | D2: 16 | E2: Campaña Q1 — optimización
A3: Ana López | B3: Marca Gamma — SEO | C3: S12 (17-21 mar) | D3: 8 | E3: Auditoría técnica
A4: Ana López | B4: Marca Delta — Branding | C4: S12 (17-21 mar) | D4: 6 | E4: Apoyo estrategia paid
A5: Luis García | B5: Marca Alpha — Social | C5: S12 (17-21 mar) | D5: 12 | E5: Creatividades mensuales
A6: Luis García | B6: Marca Delta — Branding | C6: S12 (17-21 mar) | D6: 14 | E6: Identidad visual fase 2
A7: Luis García | B7: Marca Beta — Web | C7: S12 (17-21 mar) | D7: 6 | E7: Maquetación landing
A8: María Pérez | B8: Marca Alpha — Paid | C8: S12 (17-21 mar) | D8: 10 | E8: Seguimiento semanal cliente
A9: María Pérez | B9: Marca Alpha — Social | C9: S12 (17-21 mar) | D9: 6 | E9: Revisión calendario
A10: María Pérez | B10: Marca Beta — Web | C10: S12 (17-21 mar) | D10: 8 | E10: Coordinación dev + diseño
A11: María Pérez | B11: Marca Gamma — SEO | C11: S12 (17-21 mar) | D11: 5 | E11: Revisión entregas
A12: Carlos Ruiz | B12: Marca Gamma — SEO | C12: S12 (17-21 mar) | D12: 20 | E12: Contenidos + linkbuilding
A13: Carlos Ruiz | B13: Marca Alpha — Paid | C13: S12 (17-21 mar) | D13: 8 | E13: Copy landing pages
... A50: Pablo Torres | B50: Interno — Formación | C50: S13 (24-28 mar) | D50: 3 | E50: Práctica Figma
A71: 📋 Una fila por bloque persona + proyecto + semana. Usa los desplegables para evitar errores. Las filas vacías de abajo tienen los desplegables listos.

Sheet Insights
A1: Persona | B1: Departamento | C1: Cap. neta (h) | D1: H. asignadas | E1: H. libres | F1: Utilización | G1: Estado | H1: Coste sem. (€) | I1: Nº proyectos
A2: Ana López | B2: =Equipo!B2 | C2: =Equipo!G2 | D2: =SUMIF(Asignacion!A:A,A2,Asignacion!D:D) | E2: =C2-D2 | F2: =IFERROR(D2/C2,0) | G2: =IF(F2>=1,"⛔ SOBRECARGA",IF(F2>0.9,"⚠️ RIESGO",IF(F2>0.7,"✅ ÓPTIMO","💤 BAJA CARGA"))) | H2: =D2*Equipo!H2 | I2: =COUNTIF(Asignacion!A:A,A2)
A3: Luis García | B3: =Equipo!B3 | C3: =Equipo!G3 | D3: =SUMIF(Asignacion!A:A,A3,Asignacion!D:D) | E3: =C3-D3 | F3: =IFERROR(D3/C3,0) | G3: =IF(F3>=1,"⛔ SOBRECARGA",IF(F3>0.9,"⚠️ RIESGO",IF(F3>0.7,"✅ ÓPTIMO","💤 BAJA CARGA"))) | H3: =D3*Equipo!H3 | I3: =COUNTIF(Asignacion!A:A,A3)
A4: María Pérez | B4: =Equipo!B4 | C4: =Equipo!G4 | D4: =SUMIF(Asignacion!A:A,A4,Asignacion!D:D) | E4: =C4-D4 | F4: =IFERROR(D4/C4,0) | G4: =IF(F4>=1,"⛔ SOBRECARGA",IF(F4>0.9,"⚠️ RIESGO",IF(F4>0.7,"✅ ÓPTIMO","💤 BAJA CARGA"))) | H4: =D4*Equipo!H4 | I4: =COUNTIF(Asignacion!A:A,A4)
A5: Carlos Ruiz | B5: =Equipo!B5 | C5: =Equipo!G5 | D5: =SUMIF(Asignacion!A:A,A5,Asignacion!D:D) | E5: =C5-D5 | F5: =IFERROR(D5/C5,0) | G5: =IF(F5>=1,"⛔ SOBRECARGA",IF(F5>0.9,"⚠️ RIESGO",IF(F5>0.7,"✅ ÓPTIMO","💤 BAJA CARGA"))) | H5: =D5*Equipo!H5 | I5: =COUNTIF(Asignacion!A:A,A5)
A6: Elena Martín | B6: =Equipo!B6 | C6: =Equipo!G6 | D6: =SUMIF(Asignacion!A:A,A6,Asignacion!D:D) | E6: =C6-D6 | F6: =IFERROR(D6/C6,0) | G6: =IF(F6>=1,"⛔ SOBRECARGA",IF(F6>0.9,"⚠️ RIESGO",IF(F6>0.7,"✅ ÓPTIMO","💤 BAJA CARGA"))) | H6: =D6*Equipo!H6 | I6: =COUNTIF(Asignacion!A:A,A6)
A7: Jorge Navarro | B7: =Equipo!B7 | C7: =Equipo!G7 | D7: =SUMIF(Asignacion!A:A,A7,Asignacion!D:D) | E7: =C7-D7 | F7: =IFERROR(D7/C7,0) | G7: =IF(F7>=1,"⛔ SOBRECARGA",IF(F7>0.9,"⚠️ RIESGO",IF(F7>0.7,"✅ ÓPTIMO","💤 BAJA CARGA"))) | H7: =D7*Equipo!H7 | I7: =COUNTIF(Asignacion!A:A,A7)
A8: Sara Díaz | B8: =Equipo!B8 | C8: =Equipo!G8 | D8: =SUMIF(Asignacion!A:A,A8,Asignacion!D:D) | E8: =C8-D8 | F8: =IFERROR(D8/C8,0) | G8: =IF(F8>=1,"⛔ SOBRECARGA",IF(F8>0.9,"⚠️ RIESGO",IF(F8>0.7,"✅ ÓPTIMO","💤 BAJA CARGA"))) | H8: =D8*Equipo!H8 | I8: =COUNTIF(Asignacion!A:A,A8)
A9: Pablo Torres | B9: =Equipo!B9 | C9: =Equipo!G9 | D9: =SUMIF(Asignacion!A:A,A9,Asignacion!D:D) | E9: =C9-D9 | F9: =IFERROR(D9/C9,0) | G9: =IF(F9>=1,"⛔ SOBRECARGA",IF(F9>0.9,"⚠️ RIESGO",IF(F9>0.7,"✅ ÓPTIMO","💤 BAJA CARGA"))) | H9: =D9*Equipo!H9 | I9: =COUNTIF(Asignacion!A:A,A9)
A10: TOTALES / MEDIA | C10: =SUM(C2:C9) | D10: =SUM(D2:D9) | E10: =SUM(E2:E9) | F10: =IFERROR(D10/C10,0) | H10: =SUM(H2:H9) | I10: =SUM(I2:I9)
A12: 📊 KPIs DE LA SEMANA
A13: Utilización media del equipo | B13: =F10
A14: Personas en riesgo o sobrecarga | B14: =COUNTIF(F2:F9,">"&0.9)
A15: Horas libres totales del equipo | B15: =E10
A16: Coste semanal total del equipo | B16: =H10
A17: Impuesto Excel estimado (4h PM/sem) | B17: =4*Equipo!H4
A18: Impuesto Excel anual estimado | B18: =4*Equipo!H4*52
